spatialmath_lite/__init__.py
spatialmath_lite/core.py
spatialmath_lite/operations.py
spatialmath_lite/py.typed
spatialmath_lite_hhmaozy-1.3.0.dist-info/licenses/LICENSE
spatialmath_lite_hhmaozy-1.3.0.dist-info/METADATA
spatialmath_lite_hhmaozy-1.3.0.dist-info/WHEEL
spatialmath_lite_hhmaozy-1.3.0.dist-info/top_level.txt
spatialmath_lite_hhmaozy-1.3.0.dist-info/RECORD
